{
  "generator-jhipster": {
    "applicationType": "monolith",
    "gitCompany": "",
    "baseName": "jXAntrag",
    "packageName": "com.antrag.myapp",
    "packageFolder": "com/antrag/myapp",
    "serverPort": 8080,
    "serviceDiscoveryType": false,
    "authenticationType": "jwt",
    "uaaBaseName": "../uaa",
    "cacheProvider": "ehcache",
    "enableHibernateCache": false,
    "websocket": false,
    "databaseType": "mongodb",
    "devDatabaseType": "mongodb",
    "prodDatabaseType": "mongodb",
    "searchEngine": false,
    "enableSwaggerCodegen": false,
    "messageBroker": false,
    "buildTool": "gradle",
    "useSass": true,
    "clientPackageManager": "npm",
    "testFrameworks": [],
    "enableTranslation": true,
    "nativeLanguage": "de",
    "languages": [
      "en",
      "de"
    ],
    "clientFramework": "react",
    "jhiPrefix": "jhi",
    "jhipsterVersion": "6.5.1",
    "jwtSecretKey": "MTc0MTU4NGU4ZjBiZjkzNDc4YzM1NDkzM2YwMTM3OWM0NTJmYWZkODNlNTJiZTg3YjFhYWMwZjdkNGQ0ZWVjNGU1YTgzMGJhYmI1ZmRkY2M3NzBhZTUzNmIyZTcxYTRkY2I1YWU4MzYwYTg3OWY2MzZlZDI1YjhlYjRkNjI5MDg=",
    "embeddableLaunchScript": false,
    "clientTheme": "none",
    "entitySuffix": "",
    "dtoSuffix": "DTO",
    "otherModules": [],
    "blueprints": []
  },
  "git-provider": "GitHub",
  "git-company": "Xhavit2019",
  "repository-name": "jXAntragRepository"
}